slack_logger/__init__.py
slack_logger/message_logger.py
slack_logger/utils.py
py_slack_logger-1.0.2.dist-info/METADATA
py_slack_logger-1.0.2.dist-info/WHEEL
py_slack_logger-1.0.2.dist-info/licenses/LICENSE
py_slack_logger-1.0.2.dist-info/RECORD
