Metadata-Version: 2.4
Name: py-slack-logger
Version: 1.0.2
Summary: Slack Logger is a custom message logger to Slack for Python 3
License-File: LICENSE
Requires-Python: >=3.11
Classifier: Development Status :: 5 - Production/Stable
Classifier: Intended Audience :: Developers
Classifier: License :: OSI Approved :: MIT License
Classifier: Operating System :: OS Independent
Classifier: Programming Language :: Python :: 3
Classifier: Topic :: Communications :: Chat
Requires-Dist: pyyaml (>=6.0,<7.0)
Requires-Dist: slack-sdk (>=3.37,<4.0)
Project-URL: Homepage, https://pypi.org/project/py-slack-logger/
Project-URL: Issues, https://github.com/Kayenta/py-slack-logger/issues
Project-URL: Source, https://github.com/Kayenta/py-slack-logger
